{
  "name": "Necktie",
  "type_name": "neck",
  "layer_1": {
    "zPos": 90,
    "male": "neck/tie/necktie/male/",
    "female": "neck/tie/necktie/female/",
    "muscular": "neck/tie/necktie/male/",
    "pregnant": "neck/tie/necktie/female/",
    "teen": "neck/tie/necktie/female/"
  },
  "variants": [
    "base",
    "black",
    "blue",
    "bluegray",
    "brown",
    "charcoal",
    "forest",
    "gray",
    "green",
    "lavender",
    "leather",
    "maroon",
    "navy",
    "orange",
    "pink",
    "purple",
    "red",
    "rose",
    "sky",
    "slate",
    "tan",
    "teal",
    "walnut",
    "white",
    "yellow"
  ],
  "animations": [
    "spellcast",
    "thrust",
    "walk",
    "slash",
    "shoot",
    "hurt",
    "watering",
    "idle",
    "jump",
    "run",
    "sit",
    "emote",
    "climb",
    "combat",
    "1h_slash",
    "1h_backslash",
    "1h_halfslash"
  ],
  "credits": [
    {
      "file": "neck/tie/necktie",
      "notes": "Originally by pennomi/laetissima/Makrohn, edited by bluecarrot16, animations and recolors by JaidynReiman",
      "authors": [
        "JaidynReiman",
        "bluecarrot16",
        "Thane Brimhall (pennomi)",
        "laetissima",
        "Makrohn"
      ],
      "licenses": [
        "CC-BY-SA 3.0",
        "GPL 3.0"
      ],
      "urls": [
        "https://opengameart.org/content/lpc-2-characters",
        "https://opengameart.org/content/lpc-gentleman"
      ]
    }
  ],
  "ids": {
    "base": "neck-Necktie_base",
    "black": "neck-Necktie_black",
    "blue": "neck-Necktie_bluegray",
    "brown": "neck-Necktie_brown",
    "charcoal": "neck-Necktie_charcoal",
    "forest": "neck-Necktie_forest",
    "gray": "neck-Necktie_gray",
    "green": "neck-Necktie_green",
    "lavender": "neck-Necktie_lavender",
    "leather": "neck-Necktie_leather",
    "maroon": "neck-Necktie_maroon",
    "navy": "neck-Necktie_navy",
    "orange": "neck-Necktie_orange",
    "pink": "neck-Necktie_pink",
    "purple": "neck-Necktie_purple",
    "red": "neck-Necktie_red",
    "rose": "neck-Necktie_rose",
    "sky": "neck-Necktie_sky",
    "slate": "neck-Necktie_slate",
    "tan": "neck-Necktie_tan",
    "teal": "neck-Necktie_teal",
    "walnut": "neck-Necktie_walnut",
    "white": "neck-Necktie_white",
    "yellow": "neck-Necktie_yellow"
  }
}